ssh_easy/cli.py
ssh_easy/ssheasy.py
ssheasy-1.0.0.dist-info/LICENSE
ssheasy-1.0.0.dist-info/METADATA
ssheasy-1.0.0.dist-info/WHEEL
ssheasy-1.0.0.dist-info/entry_points.txt
ssheasy-1.0.0.dist-info/top_level.txt
ssheasy-1.0.0.dist-info/RECORD
