Metadata-Version: 2.1
Name: ssheasy
Version: 1.0.0
Summary: SSHeasy is a python version of ruby gem SSHwitch which through you can manage multiple ssh key in Unix-like system. The purpose of this is to enable using different sets of keys for services such as Github, Heroku, Bitbucket, or any other that requires SSH auth.
Home-page: https://github.com/morshedmasud/ssheasy
Author: Md Morshed Alam Masud
Author-email: morshed.dev@gmail.com
License: UNKNOWN
Keywords: ssh,crypto,cryptography,security,privacy,sshwitch,sshmulti
Platform: UNKNOWN
Classifier: Programming Language :: Python :: 3.6
Classifier: License :: OSI Approved :: MIT License
Classifier: Operating System :: MacOS :: MacOS X
Classifier: Operating System :: Unix
Requires-Dist: click
Requires-Dist: crypto
Requires-Dist: pycryptodome (==3.9.7)
